https_dns_proxy/__init__.py
https_dns_proxy-1.0.1.dist-info/LICENSE
https_dns_proxy-1.0.1.dist-info/METADATA
https_dns_proxy-1.0.1.dist-info/WHEEL
https_dns_proxy-1.0.1.dist-info/entry_points.txt
https_dns_proxy-1.0.1.dist-info/top_level.txt
https_dns_proxy-1.0.1.dist-info/RECORD
